python_execute_server/__init__.py
python_execute_server/__main__.py
python_execute_server/python_repl_run.py
python_execute_server/server.py
python_execute_server/pyarmor_runtime_000000/__init__.py
python_execute_server/pyarmor_runtime_000000/darwin_universal/pyarmor_runtime.so
iflow_mcp_python_execute_server-0.1.3.dist-info/METADATA
iflow_mcp_python_execute_server-0.1.3.dist-info/WHEEL
iflow_mcp_python_execute_server-0.1.3.dist-info/entry_points.txt
iflow_mcp_python_execute_server-0.1.3.dist-info/RECORD
