Metadata-Version: 2.4
Name: iflow-mcp_python-execute-server
Version: 0.1.3
Summary: A Model Context Protocol server providing python code execution capability
Author: iflow team
License: MIT
Keywords: automation,code,llm,mcp,python
Classifier: Development Status :: 4 - Beta
Classifier: Intended Audience :: Developers
Classifier: License :: OSI Approved :: MIT License
Classifier: Programming Language :: Python :: 3
Classifier: Programming Language :: Python :: 3.10
Classifier: Programming Language :: Python :: 3.11
Classifier: Programming Language :: Python :: 3.12
Requires-Python: ==3.12.7
Requires-Dist: jieba>=0.42.1
Requires-Dist: matplotlib>=3.10.5
Requires-Dist: mcp[cli]>=1.12.4
Requires-Dist: numpy>=2.3.2
Requires-Dist: openpyxl>=3.1.5
Requires-Dist: pandas>=2.3.1
Requires-Dist: pillow>=11.3.0
Requires-Dist: pyecharts-snapshot>=0.2.0
Requires-Dist: pyecharts==2.0.8
Requires-Dist: python-docx>=1.2.0
Requires-Dist: scikit-learn>=1.7.1
Requires-Dist: seaborn>=0.13.2
Requires-Dist: selenium>=4.35.0
Requires-Dist: snapshot-selenium>=0.0.2
Requires-Dist: wordcloud>=1.9.4
